approveapi/__init__.py
approveapi-1.0.18.dist-info/METADATA
approveapi-1.0.18.dist-info/WHEEL
approveapi-1.0.18.dist-info/top_level.txt
approveapi-1.0.18.dist-info/RECORD
