Metadata-Version: 2.1
Name: approveapi
Version: 1.0.18
Summary: ApproveAPI
Home-page: https://approveapi.com
Author: UNKNOWN
Author-email: hello@approveapi.com
License: UNKNOWN
Platform: UNKNOWN
Requires-Dist: approveapi-swagger (>=1.0.13)
